personaednd/__init__.py
personaednd/attributes.py
personaednd/dice.py
personaednd/listutils.py
personaednd/shell.py
personaednd/version.py
personaednd/sources/__init__.py
personaednd/sources/reader.py
personaednd/sources/sources.yml
personaednd-0.1.6.dist-info/LICENSE
personaednd-0.1.6.dist-info/METADATA
personaednd-0.1.6.dist-info/WHEEL
personaednd-0.1.6.dist-info/entry_points.txt
personaednd-0.1.6.dist-info/top_level.txt
personaednd-0.1.6.dist-info/RECORD
