Metadata-Version: 2.1
Name: personaednd
Version: 0.1.6
Summary: Randomly generates 5th edition Dungeons & Dragons characters.
Home-page: https://github.com/sg679/personaednd
Author: Marcus T Taylor
License: MIT
Platform: UNKNOWN
Classifier: Development Status :: 4 - Beta
Classifier: Environment :: Console
Classifier: License :: OSI Approved :: MIT License
Classifier: Operating System :: OS Independent
Classifier: Programming Language :: Python :: 3
Classifier: Programming Language :: Python :: 3 :: Only
Classifier: Topic :: Games/Entertainment :: Role-Playing
Requires-Python: >=3.0
Requires-Dist: beautifulsoup4 (>=4.8)
Requires-Dist: click (>=7.0)
Requires-Dist: lxml (>=4.4)
Requires-Dist: numpy (>=1.17)
Requires-Dist: PyYAML (>=5.1)
